pynsure/__init__.py
pynsure-0.1.0.dist-info/METADATA
pynsure-0.1.0.dist-info/WHEEL
pynsure-0.1.0.dist-info/entry_points.txt
pynsure-0.1.0.dist-info/RECORD
