Metadata-Version: 2.1
Name: pynsure
Version: 0.1.0
Summary: 
Author: Justin Stitt
Author-email: justinstitt@google.com
Requires-Python: >=3.10,<4.0
Classifier: Programming Language :: Python :: 3
Classifier: Programming Language :: Python :: 3.10
Classifier: Programming Language :: Python :: 3.11
Classifier: Programming Language :: Python :: 3.12
